ni/__init__.py
ni/config/__init__.py
ni/config/config.py
ni/config/tools.py
ni/config/validator.py
ni_config-0.0.15.dist-info/LICENSE
ni_config-0.0.15.dist-info/METADATA
ni_config-0.0.15.dist-info/WHEEL
ni_config-0.0.15.dist-info/top_level.txt
ni_config-0.0.15.dist-info/RECORD
